simple_drf/__init__.py
simple_drf/api_classes.py
simple_drf/api_functions.py
simple_drf-1.0.0.dist-info/licenses/LICENSE
simple_drf-1.0.0.dist-info/METADATA
simple_drf-1.0.0.dist-info/WHEEL
simple_drf-1.0.0.dist-info/top_level.txt
simple_drf-1.0.0.dist-info/RECORD
