Metadata-Version: 2.4
Name: simple_drf
Version: 1.0.0
Summary: A Python package for quicker API development in Django.
Author-email: Samuel Chichester <samuelchichester05@gmail.com>
License: MIT License
Project-URL: Homepage, https://github.com/SamChichester/Simple-DRF
Classifier: Programming Language :: Python :: 3
Classifier: License :: OSI Approved :: MIT License
Classifier: Operating System :: OS Independent
License-File: LICENSE
Requires-Dist: django
Requires-Dist: django-rest-framework
Dynamic: license-file
